{"cameraMode":{"drawMode":0,"name":"Shaded","section":"Shading Mode"},"sceneLighting":true,"audioPlay":false,"sceneViewState":{"showFog":true,"showMaterialUpdate":false,"showSkybox":true,"showFlares":true,"showImageEffects":true,"showParticleSystems":true},"in2DMode":false,"pivot":{"x":9.333123207092286,"y":2.9337968826293947,"z":-21.014528274536134},"rotation":{"x":-0.004808989353477955,"y":-0.97957444190979,"z":0.1999071091413498,"w":-0.02353774756193161},"size":9.410274505615235,"orthographic":false}